gitmeta.py
git_meta-0.3.dist-info/licenses/LICENCE.txt
git_meta-0.3.dist-info/METADATA
git_meta-0.3.dist-info/WHEEL
git_meta-0.3.dist-info/entry_points.txt
git_meta-0.3.dist-info/top_level.txt
git_meta-0.3.dist-info/RECORD
