Metadata-Version: 2.4
Name: git-meta
Version: 0.3
Summary: Git repository manager
Home-page: https://github.com/galactics/git-meta
Author: Jules DAVID
Author-email: jules@onada.fr
Keywords: git
Classifier: Development Status :: 4 - Beta
Classifier: Intended Audience :: Developers
Classifier: License :: OSI Approved :: BSD License
Classifier: Programming Language :: Python :: 3
Classifier: Programming Language :: Python :: 3.6
Classifier: Programming Language :: Python :: 3.7
Classifier: Programming Language :: Python :: 3.8
Classifier: Programming Language :: Python :: 3.9
Classifier: Programming Language :: Python :: 3.10
Classifier: Programming Language :: Python :: 3.11
Classifier: Programming Language :: Python :: 3.12
Classifier: Programming Language :: Python :: 3.13
Classifier: Topic :: Software Development :: Version Control :: Git
License-File: LICENCE.txt
Requires-Dist: gitpython
Requires-Dist: docopt
Requires-Dist: appdirs
Requires-Dist: rich
Provides-Extra: tests
Requires-Dist: flake8; extra == "tests"
Requires-Dist: pytest; extra == "tests"
Requires-Dist: pytest-cov; extra == "tests"
Provides-Extra: dev
Requires-Dist: Sphinx; extra == "dev"
Requires-Dist: tox; extra == "dev"
Dynamic: license-file
